project/float/rtl/flop.v
/* Modified to allow loading a value */

module flop
  #(parameter Bits=1)
  (  input clk
    ,input reset
    ,input load
    ,input [Bits-1:0] load_val
    ,input [Bits-1:0] d
    ,output reg [Bits-1:0] q
  );

  always @(posedge clk) begin
    if (reset)
      q <= 'b0;
    else if (load)
      q <= load_val;
    else
      q <= d;
  end

endmodule

project/divider/rtl/division_block.v
/* verilator lint_off UNUSED */
/* 
 * Kenneth Mayer (1401529)
 * krmayer@ucsc.edu
 * division_block.v
 * This module performs multi-cycle division on its two operands and returns the result
 * when it is ready, along with a 'done' signal.
 * Credit: algorithm adapted from http://www.ece.lsu.edu/ee3755/2012f/l07.v.html
 */

module division_block(
    input 	    clk,
    input 	    reset_i,

    input 	    start_i,
    input [64-1:0]  dividend_i, 
    input [64-1:0]  divisor_i,

    output 	    done_o,
    output [64-1:0] quotient_o,
    output [64-1:0] remainder_o 
);

   reg 		    done_next;
   reg [64-1:0]     quotient_next;
   reg [128-1:0]    remainder, remainder_next;
   reg [64-1:0]     dividend, dividend_next; /* holds absolute value of dividend */
   reg [64-1:0]     divisor, divisor_next; /* holds absolute value of divisor */
   reg 		    pending, pending_next;
   reg [65-1:0]     diff;

   /* sign of the output; 1 = negative, 0 = positive  */
   reg 		    sign, sign_next;

   reg [6:0] 	    index, index_next;
   
   always @(*) begin
      pending_next = pending;
      done_next = done_o;
      quotient_next = quotient_o;
      pending_next = pending;
      dividend_next = dividend;
      divisor_next = divisor;
      index_next = index;
      sign_next = sign;
      if(start_i && !pending) begin
	 pending_next = 1'b1;
	 
	 /* Divide by zero detection  */
	 if(divisor_i == 64'b0) begin
	    done_next = 1'b1;
	    quotient_next = 64'hFFFFFFFFFFFFFFFF;
	    pending_next = 1'b0;
	 end
	 
	 sign_next = ($signed(dividend_i) < $signed(64'b0)) ^ ($signed(divisor_i) < $signed(64'b0));

	 /* Take the absolute value of the operands */
	 if($signed(dividend_i) < $signed(64'b0))
	   dividend_next = ~(dividend_i) + 64'b1;
	 else
	   dividend_next = dividend_i;
	 
	 if($signed(divisor_i) < $signed(64'b0))
	   divisor_next = ~(divisor_i) + 64'b1;
	 else
	   divisor_next = divisor_i;
	 
	 index_next = 7'd63;
	 remainder_next[63:0] = dividend_next;
      end else if(pending) begin // if (start_i && !pending)
	 diff = remainder[127:63] - {1'b0, divisor};
	 if(diff[64])
	   remainder_next = {remainder[126:0], 1'b0};
	 else
	   remainder_next = {diff[63:0], remainder[62:0], 1'b1};
	 index_next = index - 1;
	 if(index == 7'b0)
	   pending_next = 1'b0;
      end else begin
	 if(sign)
	   remainder_next[63:0] = ~(remainder[63:0]) + 64'b1;
	 done_next = 1'b1;
      end
      
   end

   flop
     #(.Bits(64)) dividend_flop
       (.clk      (clk),
	.reset    (reset_i),
	.load     (1'b0),
	.load_val (64'b0),
	.d        (dividend_next),
	.q        (dividend)
	);

   flop
     #(.Bits(64)) divisor_flop
       (.clk      (clk),
	.reset    (reset_i),
	.load     (1'b0),
	.load_val (64'b0),
	.d        (divisor_next),
	.q        (divisor)
	);

   
   flop
     #(.Bits(64)) quotient_flop
       (.clk      (clk),
	.reset    (reset_i),
	.load     (1'b0),
	.load_val (64'b0),
	.d        (remainder_next[63:0]),
	.q        (quotient_o)
	);

   flop
     #(.Bits(64)) remainder_flop
       (.clk      (clk),
	.reset    (reset_i),
	.load     (1'b0),
	.load_val (64'b0),
	.d        (remainder_next[127:64]),
	.q        (remainder_o)
	);

   flop
     #(.Bits(128)) remainder_int_flop
       (.clk      (clk),
	.reset    (reset_i),
	.load     (1'b0),
	.load_val (128'b0),
	.d        (remainder_next),
	.q        (remainder)
	);

   flop
     #(.Bits(7)) index_flop
       (.clk      (clk),
	.reset    (reset_i),
	.load     (1'b0),
	.load_val (7'b0),
	.d        (index_next),
	.q        (index)
	);

   flop
     #(.Bits(1)) pending_flop
       (.clk      (clk),
	.reset    (reset_i),
	.load     (1'b0),
	.load_val (1'b0),
	.d        (pending_next),
	.q        (pending)
	);

   flop
     #(.Bits(1)) done_flop
       (.clk      (clk),
	.reset    (reset_i),
	.load     (1'b0),
	.load_val (1'b0),
	.d        (done_next),
	.q        (done_o)
	);

   flop
     #(.Bits(1)) sign_flop
       (.clk      (clk),
	.reset    (reset_i),
	.load     (1'b0),
	.load_val (1'b0),
	.d        (sign_next),
	.q        (sign)
	);
   
endmodule // division_block
/* verilator lint_off UNUSED */

project/divider/output.vcd
$version Generated by VerilatedVcd $end
$date Fri Nov  9 13:30:37 2018
 $end
$timescale   1ns $end

 $scope module TOP $end
  $var wire  1 C clk $end
  $var wire 64 F dividend_i [63:0] $end
  $var wire 64 H divisor_i [63:0] $end
  $var wire  1 J done_o $end
  $var wire 64 K quotient_o [63:0] $end
  $var wire 64 M remainder_o [63:0] $end
  $var wire  1 D reset_i $end
  $var wire  1 E start_i $end
  $scope module division_block $end
   $var wire  1 C clk $end
   $var wire 65 / diff [64:0] $end
   $var wire 64 < dividend [63:0] $end
   $var wire 64 F dividend_i [63:0] $end
   $var wire 64 * dividend_next [63:0] $end
   $var wire 64 > divisor [63:0] $end
   $var wire 64 H divisor_i [63:0] $end
   $var wire 64 , divisor_next [63:0] $end
   $var wire  1 # done_next $end
   $var wire  1 J done_o $end
   $var wire  7 B index [6:0] $end
   $var wire  7 3 index_next [6:0] $end
   $var wire  1 @ pending $end
   $var wire  1 . pending_next $end
   $var wire 64 $ quotient_next [63:0] $end
   $var wire 64 K quotient_o [63:0] $end
   $var wire 128 8 remainder [127:0] $end
   $var wire 128 & remainder_next [127:0] $end
   $var wire 64 M remainder_o [63:0] $end
   $var wire  1 D reset_i $end
   $var wire  1 A sign $end
   $var wire  1 2 sign_next $end
   $var wire  1 E start_i $end
   $scope module dividend_flop $end
    $var wire 32 O Bits [31:0] $end
    $var wire  1 C clk $end
    $var wire 64 * d [63:0] $end
    $var wire  1 P load $end
    $var wire 64 Q load_val [63:0] $end
    $var wire 64 < q [63:0] $end
    $var wire  1 D reset $end
   $upscope $end
   $scope module divisor_flop $end
    $var wire 32 O Bits [31:0] $end
    $var wire  1 C clk $end
    $var wire 64 , d [63:0] $end
    $var wire  1 P load $end
    $var wire 64 Q load_val [63:0] $end
    $var wire 64 > q [63:0] $end
    $var wire  1 D reset $end
   $upscope $end
   $scope module done_flop $end
    $var wire 32 Z Bits [31:0] $end
    $var wire  1 C clk $end
    $var wire  1 # d [0:0] $end
    $var wire  1 P load $end
    $var wire  1 P load_val [0:0] $end
    $var wire  1 J q [0:0] $end
    $var wire  1 D reset $end
   $upscope $end
   $scope module index_flop $end
    $var wire 32 X Bits [31:0] $end
    $var wire  1 C clk $end
    $var wire  7 3 d [6:0] $end
    $var wire  1 P load $end
    $var wire  7 Y load_val [6:0] $end
    $var wire  7 B q [6:0] $end
    $var wire  1 D reset $end
   $upscope $end
   $scope module pending_flop $end
    $var wire 32 Z Bits [31:0] $end
    $var wire  1 C clk $end
    $var wire  1 . d [0:0] $end
    $var wire  1 P load $end
    $var wire  1 P load_val [0:0] $end
    $var wire  1 @ q [0:0] $end
    $var wire  1 D reset $end
   $upscope $end
   $scope module quotient_flop $end
    $var wire 32 O Bits [31:0] $end
    $var wire  1 C clk $end
    $var wire 64 4 d [63:0] $end
    $var wire  1 P load $end
    $var wire 64 Q load_val [63:0] $end
    $var wire 64 K q [63:0] $end
    $var wire  1 D reset $end
   $upscope $end
   $scope module remainder_flop $end
    $var wire 32 O Bits [31:0] $end
    $var wire  1 C clk $end
    $var wire 64 6 d [63:0] $end
    $var wire  1 P load $end
    $var wire 64 Q load_val [63:0] $end
    $var wire 64 M q [63:0] $end
    $var wire  1 D reset $end
   $upscope $end
   $scope module remainder_int_flop $end
    $var wire 32 S Bits [31:0] $end
    $var wire  1 C clk $end
    $var wire 128 & d [127:0] $end
    $var wire  1 P load $end
    $var wire 128 T load_val [127:0] $end
    $var wire 128 8 q [127:0] $end
    $var wire  1 D reset $end
   $upscope $end
   $scope module sign_flop $end
    $var wire 32 Z Bits [31:0] $end
    $var wire  1 C clk $end
    $var wire  1 2 d [0:0] $end
    $var wire  1 P load $end
    $var wire  1 P load_val [0:0] $end
    $var wire  1 A q [0:0] $end
    $var wire  1 D reset $end
   $upscope $end
  $upscope $end
 $upscope $end
$enddefinitions $end


#0
0#
b0000000000000000000000000000000000000000000000000000000000000000 $
b00000000000000000000000000000000000000000000000000000000000000000000000000000000000000000000000000000000000000000000100010101000 &
b0000000000000000000000000000000000000000000000000000100010101000 *
b0000000000000000000000000000000000000000000000000000000000000111 ,
1.
b00000000000000000000000000000000000000000000000000000000000000000 /
12
b0111111 3
b0000000000000000000000000000000000000000000000000000100010101000 4
b0000000000000000000000000000000000000000000000000000000000000000 6
b00000000000000000000000000000000000000000000000000000000000000000000000000000000000000000000000000000000000000000000000000000000 8
b0000000000000000000000000000000000000000000000000000000000000000 <
b0000000000000000000000000000000000000000000000000000000000000000 >
0@
0A
b0000000 B
1C
1D
1E
b0000000000000000000000000000000000000000000000000000100010101000 F
b1111111111111111111111111111111111111111111111111111111111111001 H
0J
b0000000000000000000000000000000000000000000000000000000000000000 K
b0000000000000000000000000000000000000000000000000000000000000000 M
b00000000000000000000000001000000 O
0P
b0000000000000000000000000000000000000000000000000000000000000000 Q
b00000000000000000000000010000000 S
b00000000000000000000000000000000000000000000000000000000000000000000000000000000000000000000000000000000000000000000000000000000 T
b00000000000000000000000000000111 X
b0000000 Y
b00000000000000000000000000000001 Z
#0
0C
#1
#1
1C
#2
0D
#2
0C
#3
#3
b0000000000000000000000000000000000000000000000000000100010101000 $
b00000000000000000000000000000000000000000000000000000000000000000000000000000000000000000000000000000000000000000001000101010000 &
b11111111111111111111111111111111111111111111111111111111111111001 /
b0111110 3
b0000000000000000000000000000000000000000000000000001000101010000 4
b00000000000000000000000000000000000000000000000000000000000000000000000000000000000000000000000000000000000000000000100010101000 8
b0000000000000000000000000000000000000000000000000000100010101000 <
b0000000000000000000000000000000000000000000000000000000000000111 >
1@
1A
b0111111 B
1C
b0000000000000000000000000000000000000000000000000000100010101000 K
#4
0E
#4
0C
#5
#5
b0000000000000000000000000000000000000000000000000001000101010000 $
b00000000000000000000000000000000000000000000000000000000000000000000000000000000000000000000000000000000000000000010001010100000 &
b0111101 3
b0000000000000000000000000000000000000000000000000010001010100000 4
b00000000000000000000000000000000000000000000000000000000000000000000000000000000000000000000000000000000000000000001000101010000 8
b0111110 B
1C
b0000000000000000000000000000000000000000000000000001000101010000 K
#6
#6
0C
#7
#7
b0000000000000000000000000000000000000000000000000010001010100000 $
b00000000000000000000000000000000000000000000000000000000000000000000000000000000000000000000000000000000000000000100010101000000 &
b0111100 3
b0000000000000000000000000000000000000000000000000100010101000000 4
b00000000000000000000000000000000000000000000000000000000000000000000000000000000000000000000000000000000000000000010001010100000 8
b0111101 B
1C
b0000000000000000000000000000000000000000000000000010001010100000 K
#8
#8
0C
#9
#9
b0000000000000000000000000000000000000000000000000100010101000000 $
b00000000000000000000000000000000000000000000000000000000000000000000000000000000000000000000000000000000000000001000101010000000 &
b0111011 3
b0000000000000000000000000000000000000000000000001000101010000000 4
b00000000000000000000000000000000000000000000000000000000000000000000000000000000000000000000000000000000000000000100010101000000 8
b0111100 B
1C
b0000000000000000000000000000000000000000000000000100010101000000 K
#10
#10
0C
#11
#11
b0000000000000000000000000000000000000000000000001000101010000000 $
b00000000000000000000000000000000000000000000000000000000000000000000000000000000000000000000000000000000000000010001010100000000 &
b0111010 3
b0000000000000000000000000000000000000000000000010001010100000000 4
b00000000000000000000000000000000000000000000000000000000000000000000000000000000000000000000000000000000000000001000101010000000 8
b0111011 B
1C
b0000000000000000000000000000000000000000000000001000101010000000 K
#12
#12
0C
#13
#13
b0000000000000000000000000000000000000000000000010001010100000000 $
b00000000000000000000000000000000000000000000000000000000000000000000000000000000000000000000000000000000000000100010101000000000 &
b0111001 3
b0000000000000000000000000000000000000000000000100010101000000000 4
b00000000000000000000000000000000000000000000000000000000000000000000000000000000000000000000000000000000000000010001010100000000 8
b0111010 B
1C
b0000000000000000000000000000000000000000000000010001010100000000 K
#14
#14
0C
#15
#15
b0000000000000000000000000000000000000000000000100010101000000000 $
b00000000000000000000000000000000000000000000000000000000000000000000000000000000000000000000000000000000000001000101010000000000 &
b0111000 3
b0000000000000000000000000000000000000000000001000101010000000000 4
b00000000000000000000000000000000000000000000000000000000000000000000000000000000000000000000000000000000000000100010101000000000 8
b0111001 B
1C
b0000000000000000000000000000000000000000000000100010101000000000 K
#16
#16
0C
#17
#17
b0000000000000000000000000000000000000000000001000101010000000000 $
b00000000000000000000000000000000000000000000000000000000000000000000000000000000000000000000000000000000000010001010100000000000 &
b0110111 3
b0000000000000000000000000000000000000000000010001010100000000000 4
b00000000000000000000000000000000000000000000000000000000000000000000000000000000000000000000000000000000000001000101010000000000 8
b0111000 B
1C
b0000000000000000000000000000000000000000000001000101010000000000 K
#18
#18
0C
#19
#19
b0000000000000000000000000000000000000000000010001010100000000000 $
b00000000000000000000000000000000000000000000000000000000000000000000000000000000000000000000000000000000000100010101000000000000 &
b0110110 3
b0000000000000000000000000000000000000000000100010101000000000000 4
b00000000000000000000000000000000000000000000000000000000000000000000000000000000000000000000000000000000000010001010100000000000 8
b0110111 B
1C
b0000000000000000000000000000000000000000000010001010100000000000 K
#20
#20
0C
#21
#21
b0000000000000000000000000000000000000000000100010101000000000000 $
b00000000000000000000000000000000000000000000000000000000000000000000000000000000000000000000000000000000001000101010000000000000 &
b0110101 3
b0000000000000000000000000000000000000000001000101010000000000000 4
b00000000000000000000000000000000000000000000000000000000000000000000000000000000000000000000000000000000000100010101000000000000 8
b0110110 B
1C
b0000000000000000000000000000000000000000000100010101000000000000 K
#22
#22
0C
#23
#23
b0000000000000000000000000000000000000000001000101010000000000000 $
b00000000000000000000000000000000000000000000000000000000000000000000000000000000000000000000000000000000010001010100000000000000 &
b0110100 3
b0000000000000000000000000000000000000000010001010100000000000000 4
b00000000000000000000000000000000000000000000000000000000000000000000000000000000000000000000000000000000001000101010000000000000 8
b0110101 B
1C
b0000000000000000000000000000000000000000001000101010000000000000 K
#24
#24
0C
#25
#25
b0000000000000000000000000000000000000000010001010100000000000000 $
b00000000000000000000000000000000000000000000000000000000000000000000000000000000000000000000000000000000100010101000000000000000 &
b0110011 3
b0000000000000000000000000000000000000000100010101000000000000000 4
b00000000000000000000000000000000000000000000000000000000000000000000000000000000000000000000000000000000010001010100000000000000 8
b0110100 B
1C
b0000000000000000000000000000000000000000010001010100000000000000 K
#26
#26
0C
#27
#27
b0000000000000000000000000000000000000000100010101000000000000000 $
b00000000000000000000000000000000000000000000000000000000000000000000000000000000000000000000000000000001000101010000000000000000 &
b0110010 3
b0000000000000000000000000000000000000001000101010000000000000000 4
b00000000000000000000000000000000000000000000000000000000000000000000000000000000000000000000000000000000100010101000000000000000 8
b0110011 B
1C
b0000000000000000000000000000000000000000100010101000000000000000 K
#28
#28
0C
#29
#29
b0000000000000000000000000000000000000001000101010000000000000000 $
b00000000000000000000000000000000000000000000000000000000000000000000000000000000000000000000000000000010001010100000000000000000 &
b0110001 3
b0000000000000000000000000000000000000010001010100000000000000000 4
b00000000000000000000000000000000000000000000000000000000000000000000000000000000000000000000000000000001000101010000000000000000 8
b0110010 B
1C
b0000000000000000000000000000000000000001000101010000000000000000 K
#30
#30
0C
#31
#31
b0000000000000000000000000000000000000010001010100000000000000000 $
b00000000000000000000000000000000000000000000000000000000000000000000000000000000000000000000000000000100010101000000000000000000 &
b0110000 3
b0000000000000000000000000000000000000100010101000000000000000000 4
b00000000000000000000000000000000000000000000000000000000000000000000000000000000000000000000000000000010001010100000000000000000 8
b0110001 B
1C
b0000000000000000000000000000000000000010001010100000000000000000 K
#32
#32
0C
#33
#33
b0000000000000000000000000000000000000100010101000000000000000000 $
b00000000000000000000000000000000000000000000000000000000000000000000000000000000000000000000000000001000101010000000000000000000 &
b0101111 3
b0000000000000000000000000000000000001000101010000000000000000000 4
b00000000000000000000000000000000000000000000000000000000000000000000000000000000000000000000000000000100010101000000000000000000 8
b0110000 B
1C
b0000000000000000000000000000000000000100010101000000000000000000 K
#34
#34
0C
#35
#35
b0000000000000000000000000000000000001000101010000000000000000000 $
b00000000000000000000000000000000000000000000000000000000000000000000000000000000000000000000000000010001010100000000000000000000 &
b0101110 3
b0000000000000000000000000000000000010001010100000000000000000000 4
b00000000000000000000000000000000000000000000000000000000000000000000000000000000000000000000000000001000101010000000000000000000 8
b0101111 B
1C
b0000000000000000000000000000000000001000101010000000000000000000 K
#36
#36
0C
#37
#37
b0000000000000000000000000000000000010001010100000000000000000000 $
b00000000000000000000000000000000000000000000000000000000000000000000000000000000000000000000000000100010101000000000000000000000 &
b0101101 3
b0000000000000000000000000000000000100010101000000000000000000000 4
b00000000000000000000000000000000000000000000000000000000000000000000000000000000000000000000000000010001010100000000000000000000 8
b0101110 B
1C
b0000000000000000000000000000000000010001010100000000000000000000 K
#38
#38
0C
#39
#39
b0000000000000000000000000000000000100010101000000000000000000000 $
b00000000000000000000000000000000000000000000000000000000000000000000000000000000000000000000000001000101010000000000000000000000 &
b0101100 3
b0000000000000000000000000000000001000101010000000000000000000000 4
b00000000000000000000000000000000000000000000000000000000000000000000000000000000000000000000000000100010101000000000000000000000 8
b0101101 B
1C
b0000000000000000000000000000000000100010101000000000000000000000 K
#40
#40
0C
#41
#41
b0000000000000000000000000000000001000101010000000000000000000000 $
b00000000000000000000000000000000000000000000000000000000000000000000000000000000000000000000000010001010100000000000000000000000 &
b0101011 3
b0000000000000000000000000000000010001010100000000000000000000000 4
b00000000000000000000000000000000000000000000000000000000000000000000000000000000000000000000000001000101010000000000000000000000 8
b0101100 B
1C
b0000000000000000000000000000000001000101010000000000000000000000 K
#42
#42
0C
#43
#43
b0000000000000000000000000000000010001010100000000000000000000000 $
b00000000000000000000000000000000000000000000000000000000000000000000000000000000000000000000000100010101000000000000000000000000 &
b0101010 3
b0000000000000000000000000000000100010101000000000000000000000000 4
b00000000000000000000000000000000000000000000000000000000000000000000000000000000000000000000000010001010100000000000000000000000 8
b0101011 B
1C
b0000000000000000000000000000000010001010100000000000000000000000 K
#44
#44
0C
#45
#45
b0000000000000000000000000000000100010101000000000000000000000000 $
b00000000000000000000000000000000000000000000000000000000000000000000000000000000000000000000001000101010000000000000000000000000 &
b0101001 3
b0000000000000000000000000000001000101010000000000000000000000000 4
b00000000000000000000000000000000000000000000000000000000000000000000000000000000000000000000000100010101000000000000000000000000 8
b0101010 B
1C
b0000000000000000000000000000000100010101000000000000000000000000 K
#46
#46
0C
#47
#47
b0000000000000000000000000000001000101010000000000000000000000000 $
b00000000000000000000000000000000000000000000000000000000000000000000000000000000000000000000010001010100000000000000000000000000 &
b0101000 3
b0000000000000000000000000000010001010100000000000000000000000000 4
b00000000000000000000000000000000000000000000000000000000000000000000000000000000000000000000001000101010000000000000000000000000 8
b0101001 B
1C
b0000000000000000000000000000001000101010000000000000000000000000 K
#48
#48
0C
#49
#49
b0000000000000000000000000000010001010100000000000000000000000000 $
b00000000000000000000000000000000000000000000000000000000000000000000000000000000000000000000100010101000000000000000000000000000 &
b0100111 3
b0000000000000000000000000000100010101000000000000000000000000000 4
b00000000000000000000000000000000000000000000000000000000000000000000000000000000000000000000010001010100000000000000000000000000 8
b0101000 B
1C
b0000000000000000000000000000010001010100000000000000000000000000 K
#50
#50
0C
#51
#51
b0000000000000000000000000000100010101000000000000000000000000000 $
b00000000000000000000000000000000000000000000000000000000000000000000000000000000000000000001000101010000000000000000000000000000 &
b0100110 3
b0000000000000000000000000001000101010000000000000000000000000000 4
b00000000000000000000000000000000000000000000000000000000000000000000000000000000000000000000100010101000000000000000000000000000 8
b0100111 B
1C
b0000000000000000000000000000100010101000000000000000000000000000 K
#52
#52
0C
#53
#53
b0000000000000000000000000001000101010000000000000000000000000000 $
b00000000000000000000000000000000000000000000000000000000000000000000000000000000000000000010001010100000000000000000000000000000 &
b0100101 3
b0000000000000000000000000010001010100000000000000000000000000000 4
b00000000000000000000000000000000000000000000000000000000000000000000000000000000000000000001000101010000000000000000000000000000 8
b0100110 B
1C
b0000000000000000000000000001000101010000000000000000000000000000 K
#54
#54
0C
#55
#55
b0000000000000000000000000010001010100000000000000000000000000000 $
b00000000000000000000000000000000000000000000000000000000000000000000000000000000000000000100010101000000000000000000000000000000 &
b0100100 3
b0000000000000000000000000100010101000000000000000000000000000000 4
b00000000000000000000000000000000000000000000000000000000000000000000000000000000000000000010001010100000000000000000000000000000 8
b0100101 B
1C
b0000000000000000000000000010001010100000000000000000000000000000 K
#56
#56
0C
#57
#57
b0000000000000000000000000100010101000000000000000000000000000000 $
b00000000000000000000000000000000000000000000000000000000000000000000000000000000000000001000101010000000000000000000000000000000 &
b0100011 3
b0000000000000000000000001000101010000000000000000000000000000000 4
b00000000000000000000000000000000000000000000000000000000000000000000000000000000000000000100010101000000000000000000000000000000 8
b0100100 B
1C
b0000000000000000000000000100010101000000000000000000000000000000 K
#58
#58
0C
#59
#59
b0000000000000000000000001000101010000000000000000000000000000000 $
b00000000000000000000000000000000000000000000000000000000000000000000000000000000000000010001010100000000000000000000000000000000 &
b0100010 3
b0000000000000000000000010001010100000000000000000000000000000000 4
b00000000000000000000000000000000000000000000000000000000000000000000000000000000000000001000101010000000000000000000000000000000 8
b0100011 B
1C
b0000000000000000000000001000101010000000000000000000000000000000 K
#60
#60
0C
#61
#61
b0000000000000000000000010001010100000000000000000000000000000000 $
b00000000000000000000000000000000000000000000000000000000000000000000000000000000000000100010101000000000000000000000000000000000 &
b0100001 3
b0000000000000000000000100010101000000000000000000000000000000000 4
b00000000000000000000000000000000000000000000000000000000000000000000000000000000000000010001010100000000000000000000000000000000 8
b0100010 B
1C
b0000000000000000000000010001010100000000000000000000000000000000 K
#62
#62
0C
#63
#63
b0000000000000000000000100010101000000000000000000000000000000000 $
b00000000000000000000000000000000000000000000000000000000000000000000000000000000000001000101010000000000000000000000000000000000 &
b0100000 3
b0000000000000000000001000101010000000000000000000000000000000000 4
b00000000000000000000000000000000000000000000000000000000000000000000000000000000000000100010101000000000000000000000000000000000 8
b0100001 B
1C
b0000000000000000000000100010101000000000000000000000000000000000 K
#64
#64
0C
#65
#65
b0000000000000000000001000101010000000000000000000000000000000000 $
b00000000000000000000000000000000000000000000000000000000000000000000000000000000000010001010100000000000000000000000000000000000 &
b0011111 3
b0000000000000000000010001010100000000000000000000000000000000000 4
b00000000000000000000000000000000000000000000000000000000000000000000000000000000000001000101010000000000000000000000000000000000 8
b0100000 B
1C
b0000000000000000000001000101010000000000000000000000000000000000 K
#66
#66
0C
#67
#67
b0000000000000000000010001010100000000000000000000000000000000000 $
b00000000000000000000000000000000000000000000000000000000000000000000000000000000000100010101000000000000000000000000000000000000 &
b0011110 3
b0000000000000000000100010101000000000000000000000000000000000000 4
b00000000000000000000000000000000000000000000000000000000000000000000000000000000000010001010100000000000000000000000000000000000 8
b0011111 B
1C
b0000000000000000000010001010100000000000000000000000000000000000 K
#68
#68
0C
#69
#69
b0000000000000000000100010101000000000000000000000000000000000000 $
b00000000000000000000000000000000000000000000000000000000000000000000000000000000001000101010000000000000000000000000000000000000 &
b0011101 3
b0000000000000000001000101010000000000000000000000000000000000000 4
b00000000000000000000000000000000000000000000000000000000000000000000000000000000000100010101000000000000000000000000000000000000 8
b0011110 B
1C
b0000000000000000000100010101000000000000000000000000000000000000 K
#70
#70
0C
#71
#71
b0000000000000000001000101010000000000000000000000000000000000000 $
b00000000000000000000000000000000000000000000000000000000000000000000000000000000010001010100000000000000000000000000000000000000 &
b0011100 3
b0000000000000000010001010100000000000000000000000000000000000000 4
b00000000000000000000000000000000000000000000000000000000000000000000000000000000001000101010000000000000000000000000000000000000 8
b0011101 B
1C
b0000000000000000001000101010000000000000000000000000000000000000 K
#72
#72
0C
#73
#73
b0000000000000000010001010100000000000000000000000000000000000000 $
b00000000000000000000000000000000000000000000000000000000000000000000000000000000100010101000000000000000000000000000000000000000 &
b0011011 3
b0000000000000000100010101000000000000000000000000000000000000000 4
b00000000000000000000000000000000000000000000000000000000000000000000000000000000010001010100000000000000000000000000000000000000 8
b0011100 B
1C
b0000000000000000010001010100000000000000000000000000000000000000 K
#74
#74
0C
#75
#75
b0000000000000000100010101000000000000000000000000000000000000000 $
b00000000000000000000000000000000000000000000000000000000000000000000000000000001000101010000000000000000000000000000000000000000 &
b0011010 3
b0000000000000001000101010000000000000000000000000000000000000000 4
b00000000000000000000000000000000000000000000000000000000000000000000000000000000100010101000000000000000000000000000000000000000 8
b0011011 B
1C
b0000000000000000100010101000000000000000000000000000000000000000 K
#76
#76
0C
#77
#77
b0000000000000001000101010000000000000000000000000000000000000000 $
b00000000000000000000000000000000000000000000000000000000000000000000000000000010001010100000000000000000000000000000000000000000 &
b0011001 3
b0000000000000010001010100000000000000000000000000000000000000000 4
b00000000000000000000000000000000000000000000000000000000000000000000000000000001000101010000000000000000000000000000000000000000 8
b0011010 B
1C
b0000000000000001000101010000000000000000000000000000000000000000 K
#78
#78
0C
#79
#79
b0000000000000010001010100000000000000000000000000000000000000000 $
b00000000000000000000000000000000000000000000000000000000000000000000000000000100010101000000000000000000000000000000000000000000 &
b0011000 3
b0000000000000100010101000000000000000000000000000000000000000000 4
b00000000000000000000000000000000000000000000000000000000000000000000000000000010001010100000000000000000000000000000000000000000 8
b0011001 B
1C
b0000000000000010001010100000000000000000000000000000000000000000 K
#80
#80
0C
#81
#81
b0000000000000100010101000000000000000000000000000000000000000000 $
b00000000000000000000000000000000000000000000000000000000000000000000000000001000101010000000000000000000000000000000000000000000 &
b0010111 3
b0000000000001000101010000000000000000000000000000000000000000000 4
b00000000000000000000000000000000000000000000000000000000000000000000000000000100010101000000000000000000000000000000000000000000 8
b0011000 B
1C
b0000000000000100010101000000000000000000000000000000000000000000 K
#82
#82
0C
#83
#83
b0000000000001000101010000000000000000000000000000000000000000000 $
b00000000000000000000000000000000000000000000000000000000000000000000000000010001010100000000000000000000000000000000000000000000 &
b0010110 3
b0000000000010001010100000000000000000000000000000000000000000000 4
b00000000000000000000000000000000000000000000000000000000000000000000000000001000101010000000000000000000000000000000000000000000 8
b0010111 B
1C
b0000000000001000101010000000000000000000000000000000000000000000 K
#84
#84
0C
#85
#85
b0000000000010001010100000000000000000000000000000000000000000000 $
b00000000000000000000000000000000000000000000000000000000000000000000000000100010101000000000000000000000000000000000000000000000 &
b0010101 3
b0000000000100010101000000000000000000000000000000000000000000000 4
b00000000000000000000000000000000000000000000000000000000000000000000000000010001010100000000000000000000000000000000000000000000 8
b0010110 B
1C
b0000000000010001010100000000000000000000000000000000000000000000 K
#86
#86
0C
#87
#87
b0000000000100010101000000000000000000000000000000000000000000000 $
b00000000000000000000000000000000000000000000000000000000000000000000000001000101010000000000000000000000000000000000000000000000 &
b0010100 3
b0000000001000101010000000000000000000000000000000000000000000000 4
b00000000000000000000000000000000000000000000000000000000000000000000000000100010101000000000000000000000000000000000000000000000 8
b0010101 B
1C
b0000000000100010101000000000000000000000000000000000000000000000 K
#88
#88
0C
#89
#89
b0000000001000101010000000000000000000000000000000000000000000000 $
b00000000000000000000000000000000000000000000000000000000000000000000000010001010100000000000000000000000000000000000000000000000 &
b0010011 3
b0000000010001010100000000000000000000000000000000000000000000000 4
b00000000000000000000000000000000000000000000000000000000000000000000000001000101010000000000000000000000000000000000000000000000 8
b0010100 B
1C
b0000000001000101010000000000000000000000000000000000000000000000 K
#90
#90
0C
#91
#91
b0000000010001010100000000000000000000000000000000000000000000000 $
b00000000000000000000000000000000000000000000000000000000000000000000000100010101000000000000000000000000000000000000000000000000 &
b0010010 3
b0000000100010101000000000000000000000000000000000000000000000000 4
b00000000000000000000000000000000000000000000000000000000000000000000000010001010100000000000000000000000000000000000000000000000 8
b0010011 B
1C
b0000000010001010100000000000000000000000000000000000000000000000 K
#92
#92
0C
#93
#93
b0000000100010101000000000000000000000000000000000000000000000000 $
b00000000000000000000000000000000000000000000000000000000000000000000001000101010000000000000000000000000000000000000000000000000 &
b0010001 3
b0000001000101010000000000000000000000000000000000000000000000000 4
b00000000000000000000000000000000000000000000000000000000000000000000000100010101000000000000000000000000000000000000000000000000 8
b0010010 B
1C
b0000000100010101000000000000000000000000000000000000000000000000 K
#94
#94
0C
#95
#95
b0000001000101010000000000000000000000000000000000000000000000000 $
b00000000000000000000000000000000000000000000000000000000000000000000010001010100000000000000000000000000000000000000000000000000 &
b0010000 3
b0000010001010100000000000000000000000000000000000000000000000000 4
b00000000000000000000000000000000000000000000000000000000000000000000001000101010000000000000000000000000000000000000000000000000 8
b0010001 B
1C
b0000001000101010000000000000000000000000000000000000000000000000 K
#96
#96
0C
#97
#97
b0000010001010100000000000000000000000000000000000000000000000000 $
b00000000000000000000000000000000000000000000000000000000000000000000100010101000000000000000000000000000000000000000000000000000 &
b0001111 3
b0000100010101000000000000000000000000000000000000000000000000000 4
b00000000000000000000000000000000000000000000000000000000000000000000010001010100000000000000000000000000000000000000000000000000 8
b0010000 B
1C
b0000010001010100000000000000000000000000000000000000000000000000 K
#98
#98
0C
#99
#99
b0000100010101000000000000000000000000000000000000000000000000000 $
b00000000000000000000000000000000000000000000000000000000000000000001000101010000000000000000000000000000000000000000000000000000 &
b0001110 3
b0001000101010000000000000000000000000000000000000000000000000000 4
b00000000000000000000000000000000000000000000000000000000000000000000100010101000000000000000000000000000000000000000000000000000 8
b0001111 B
1C
b0000100010101000000000000000000000000000000000000000000000000000 K
#100
#100
0C
#101
